djoptimizely/__init__.py
djoptimizely/admin.py
djoptimizely/apps.py
djoptimizely/client.py
djoptimizely/middleware.py
djoptimizely/mixins.py
djoptimizely/models.py
djoptimizely/services.py
djoptimizely/settings.py
djoptimizely/tests.py
djoptimizely/urls.py
djoptimizely/views.py
djoptimizely/migrations/0001_initial.py
djoptimizely/migrations/__init__.py
djoptimizely/templatetags/__init__.py
djoptimizely/templatetags/djoptimizely_tags.py
djoptimizely/templatetags/optimizely_tags.py
djoptimizely/utils/__init__.py
djoptimizely/utils/datafile.py
djoptimizely/utils/helpers.py
djoptimizely/utils/webhook.py
dj_optimizely-0.0.8.dist-info/LICENSE.txt
dj_optimizely-0.0.8.dist-info/METADATA
dj_optimizely-0.0.8.dist-info/WHEEL
dj_optimizely-0.0.8.dist-info/top_level.txt
dj_optimizely-0.0.8.dist-info/RECORD
