Metadata-Version: 2.1
Name: dj-optimizely
Version: 0.0.8
Summary: Store Optimizely datafile in a Django model
Home-page: https://github.com/genesluder/dj-optimizely
Author: Gene Sluder
Author-email: gene@gobiko.com
License: UNKNOWN
Project-URL: Bug Tracker, https://github.com/genesluder/dj-optimizely/issues
Platform: UNKNOWN
Classifier: Programming Language :: Python :: 3
Classifier: License :: OSI Approved :: MIT License
Classifier: Operating System :: OS Independent
Requires-Python: >=3.6
Requires-Dist: django
Requires-Dist: requests
Requires-Dist: optimizely-sdk
